UART_RX_simple/UART_RX_simple.v
module UART_RX_simple#(parameter BAUD_RATE = 115200,
                         parameter PARITY = 0,
                         parameter STOP = 1,
                         parameter CLK_FREQ_HZ = 33330000
                        )(
                          input wire clk, //CLK_FREQ_HZ is this frequency
                          input wire serial_rx,
                          output reg [7:0] rx_byte = 0,
                          output reg uart_data_redy
                        );

  reg [3:0] bit_state = IDLE;
  reg [3:0] bit_count = 0;
  reg [9:0] uart_clk_divider = 0;
  reg uart_clk = 0;

  //Bit states
  parameter IDLE = 0,
            START_BIT = 1,
            DATA_BITS = 2,
            PARITY_BIT = 3,
            STOP_BIT = 4;


  parameter BAUD_RATE_HALV_PERIOD_IN_CLKS = CLK_FREQ_HZ/(BAUD_RATE*2);

  //UART clk
  always@(posedge clk)
  begin
    uart_clk_divider <= uart_clk_divider + 1;

    if( IDLE != bit_state )
    begin
      if( BAUD_RATE_HALV_PERIOD_IN_CLKS <= uart_clk_divider )
      begin
        uart_clk <= ~uart_clk;
        uart_clk_divider <= 0;
      end
    end
    else if( (IDLE == bit_state) && (0 == serial_rx) )
    begin
      uart_clk <= 1;
      uart_clk_divider <= 0;
    end
    else
    begin
      uart_clk <= 0;
      uart_clk_divider <= 0;
    end
  end

  //UART statemachine
  always@(posedge uart_clk)
  begin
    bit_count <= bit_count + 3'd1;
    case(bit_state)

      IDLE:
     begin
        uart_data_redy <= 0;
        bit_state <= START_BIT;
      end

      START_BIT:
      begin
        bit_state <= DATA_BITS;
      end

      DATA_BITS:
      begin
        if( 9 <= bit_count )
        begin
          if(PARITY)
            bit_state <= PARITY_BIT;
          else
          begin
            uart_data_redy <= 1;
            bit_state <= STOP_BIT;
          end

        end
      end

      PARITY_BIT:
      begin
        bit_state <= STOP_BIT;
      end

      STOP_BIT:
      begin
        bit_count <= 0;
        bit_state <= IDLE;
      end
    endcase
  end

  //Make the received byte
  always@(negedge uart_clk)
  begin
    if(DATA_BITS == bit_state )
    begin
        rx_byte <= { serial_rx, rx_byte[7:1] };
    end
  end

endmodule

UART_RX_simple/UART_RX_simple_tb.v
`timescale 1 ns/1ps
module UART_RX_simple_tb;
  //DUT inputs
  reg clk_tb = 0;
  reg [7:0] byte_tb = 8'h88;
  reg serial_data_tb = 1;

  //Internals
  reg [3:0] state_tb = INIT;
  integer clock_count = 0;
  integer count_finish_tb = 0;
  //States
  parameter INIT = 0,
            SEND = 1,
            FINISH = 2;

  parameter FREQ_HZ = 33330000; //Change for other clk resource.
  parameter BAUD_RATE_TB = 115200;
  parameter SEND_BYTE_CLOCKS = 10 * FREQ_HZ/BAUD_RATE_TB;

  UART_RX_simple #(.BAUD_RATE(BAUD_RATE_TB),
                   .PARITY(0),
                   .STOP(1),
                   .CLK_FREQ_HZ( FREQ_HZ ))
                 dut(
                   .clk(clk_tb), //Input
                   .serial_rx(serial_data_tb), //Input
                   .rx_byte(), //Output
                   .uart_data_redy()//Output
                 );



  always@(posedge clk_tb)
  begin
    clock_count <= clock_count + 1;
    case(state_tb)

      INIT:
      begin
        clock_count <= 0;
        serial_data_tb <= 0;
        state_tb <= SEND;
      end

      SEND:
      begin
        if( 290 <= clock_count && 2600 >= clock_count)
        begin
          if( 0 == clock_count % 289 )
            serial_data_tb <= ~serial_data_tb;
        end
        else
          if(2600 < clock_count)
          begin
            serial_data_tb <= 1;
            state_tb <= FINISH;
          end
      end

      FINISH:
      begin
        if(3500 <= clock_count)
          state_tb <= INIT;
      end

    endcase
  end

  //Clock
  always
  begin
    #15
     clk_tb = ~clk_tb;
    count_finish_tb = count_finish_tb + 1;
    if (count_finish_tb == 15'h4800)
    begin
      //#20 $fclose(logFile);

      $finish;
    end
  end

  //Dumpfile
  initial
  begin
    $dumpfile("UART_RX_simple.vcd");
    $dumpvars(0, UART_RX_simple_tb);
    $dumpvars(0, dut);
  end


endmodule

UART_RX_simple/UART_RX_simple.vcd
$date
	Tue Jun 13 11:40:56 2023
$end
$version
	Icarus Verilog
$end
$timescale
	1ps
$end
$scope module UART_RX_simple_tb $end
$var reg 8 ! byte_tb [7:0] $end
$var reg 1 " clk_tb $end
$var reg 1 # serial_data_tb $end
$var reg 4 $ state_tb [3:0] $end
$var integer 32 % clock_count [31:0] $end
$var integer 32 & count_finish_tb [31:0] $end
$scope module dut $end
$var wire 1 " clk $end
$var wire 1 # serial_rx $end
$var reg 4 ' bit_count [3:0] $end
$var reg 4 ( bit_state [3:0] $end
$var reg 8 ) rx_byte [7:0] $end
$var reg 1 * uart_clk $end
$var reg 10 + uart_clk_divider [9:0] $end
$var reg 1 , uart_data_redy $end
$upscope $end
$upscope $end
$scope module UART_RX_simple_tb $end
$scope module dut $end
$upscope $end
$upscope $end
$enddefinitions $end
#0
$dumpvars
x,
b0 +
0*
b0 )
b0 (
b0 '
b0 &
b0 %
b0 $
1#
0"
b10001000 !
$end
#15000
b0 +
b1 $
0#
b0 %
b1 &
1"
#30000
b10 &
0"
#45000
b1 (
0,
b1 '
b1 %
1*
b0 +
b11 &
1"
#60000
b100 &
0"
#75000
b1 +
b10 %
b101 &
1"
#90000
b110 &
0"
#105000
b11 %
b10 +
b111 &
1"
#120000
b1000 &
0"
#135000
b11 +
b100 %
b1001 &
1"
#150000
b1010 &
0"
#165000
b101 %
b100 +
b1011 &
1"
#180000
b1100 &
0"
#195000
b101 +
b110 %
b1101 &
1"
#210000
b1110 &
0"
#225000
b111 %
b110 +
b1111 &
1"
#240000
b10000 &
0"
#255000
b111 +
b1000 %
b10001 &
1"
#270000
b10010 &
0"
#285000
b1001 %
b1000 +
b10011 &
1"
#300000
b10100 &
0"
#315000
b1001 +
b1010 %
b10101 &
1"
#330000
b10110 &
0"
#345000
b1011 %
b1010 +
b10111 &
1"
#360000
b11000 &
0"
#375000
b1011 +
b1100 %
b11001 &
1"
#390000
b11010 &
0"
#405000
b1101 %
b1100 +
b11011 &
1"
#420000
b11100 &
0"
#435000
b1101 +
b1110 %
b11101 &
1"
#450000
b11110 &
0"
#465000
b1111 %
b1110 +
b11111 &
1"
#480000
b100000 &
0"
#495000
b1111 +
b10000 %
b100001 &
1"
#510000
b100010 &
0"
#525000
b10001 %
b10000 +
b100011 &
1"
#540000
b100100 &
0"
#555000
b10001 +
b10010 %
b100101 &
1"
#570000
b100110 &
0"
#585000
b10011 %
b10010 +
b100111 &
1"
#600000
b101000 &
0"
#615000
b10011 +
b10100 %
b101001 &
1"
#630000
b101010 &
0"
#645000
b10101 %
b10100 +
b101011 &
1"
#660000
b101100 &
0"
#675000
b10101 +
b10110 %
b101101 &
1"
#690000
b101110 &
0"
#705000
b10111 %
b10110 +
b101111 &
1"
#720000
b110000 &
0"
#735000
b10111 +
b11000 %
b110001 &
1"
#750000
b110010 &
0"
#765000
b11001 %
b11000 +
b110011 &
1"
#780000
b110100 &
0"
#795000
b11001 +
b11010 %
b110101 &
1"
#810000
b110110 &
0"
#825000
b11011 %
b11010 +
b110111 &
1"
#840000
b111000 &
0"
#855000
b11011 +
b11100 %
b111001 &
1"
#870000
b111010 &
0"
#885000
b11101 %
b11100 +
b111011 &
1"
#900000
b111100 &
0"
#915000
b11101 +
b11110 %
b111101 &
1"
#930000
b111110 &
0"
#945000
b11111 %
b11110 +
b111111 &
1"
#960000
b1000000 &
0"
#975000
b11111 +
b100000 %
b1000001 &
1"
#990000
b1000010 &
0"
#1005000
b100001 %
b100000 +
b1000011 &
1"
#1020000
b1000100 &
0"
#1035000
b100001 +
b100010 %
b1000101 &
1"
#1050000
b1000110 &
0"
#1065000
b100011 %
b100010 +
b1000111 &
1"
#1080000
b1001000 &
0"
#1095000
b100011 +
b100100 %
b1001001 &
1"
#1110000
b1001010 &
0"
#1125000
b100101 %
b100100 +
b1001011 &
1"
#1140000
b1001100 &
0"
#1155000
b100101 +
b100110 %
b1001101 &
1"
#1170000
b1001110 &
0"
#1185000
b100111 %
b100110 +
b1001111 &
1"
#1200000
b1010000 &
0"
#1215000
b100111 +
b101000 %
b1010001 &
1"
#1230000
b1010010 &
0"
#1245000
b101001 %
b101000 +
b1010011 &
1"
#1260000
b1010100 &
0"
#1275000
b101001 +
b101010 %
b1010101 &
1"
#1290000
b1010110 &
0"
#1305000
b101011 %
b101010 +
b1010111 &
1"
#1320000
b1011000 &
0"
#1335000
b101011 +
b101100 %
b1011001 &
1"
#1350000
b1011010 &
0"
#1365000
b101101 %
b101100 +
b1011011 &
1"
#1380000
b1011100 &
0"
#1395000
b101101 +
b101110 %
b1011101 &
1"
#1410000
b1011110 &
0"
#1425000
b101111 %
b101110 +
b1011111 &
1"
#1440000
b1100000 &
0"
#1455000
b101111 +
b110000 %
b1100001 &
1"
#1470000
b1100010 &
0"
#1485000
b110001 %
b110000 +
b1100011 &
1"
#1500000
b1100100 &
0"
#1515000
b110001 +
b110010 %
b1100101 &
1"
#1530000
b1100110 &
0"
#1545000
b110011 %
b110010 +
b1100111 &
1"
#1560000
b1101000 &
0"
#1575000
b110011 +
b110100 %
b1101001 &
1"
#1590000
b1101010 &
0"
#1605000
b110101 %
b110100 +
b1101011 &
1"
#1620000
b1101100 &
0"
#1635000
b110101 +
b110110 %
b1101101 &
1"
#1650000
b1101110 &
0"
#1665000
b110111 %
b110110 +
b1101111 &
1"
#1680000
b1110000 &
0"
#1695000
b110111 +
b111000 %
b1110001 &
1"
#1710000
b1110010 &
0"
#1725000
b111001 %
b111000 +
b1110011 &
1"
#1740000
b1110100 &
0"
#1755000
b111001 +
b111010 %
b1110101 &
1"
#1770000
b1110110 &
0"
#1785000
b111011 %
b111010 +
b1110111 &
1"
#1800000
b1111000 &
0"
#1815000
b111011 +
b111100 %
b1111001 &
1"
#1830000
b1111010 &
0"
#1845000
b111101 %
b111100 +
b1111011 &
1"
#1860000
b1111100 &
0"
#1875000
b111101 +
b111110 %
b1111101 &
1"
#1890000
b1111110 &
0"
#1905000
b111111 %
b111110 +
b1111111 &
1"
#1920000
b10000000 &
0"
#1935000
b111111 +
b1000000 %
b10000001 &
1"
#1950000
b10000010 &
0"
#1965000
b1000001 %
b1000000 +
b10000011 &
1"
#1980000
b10000100 &
0"
#1995000
b1000001 +
b1000010 %
b10000101 &
1"
#2010000
b10000110 &
0"
#2025000
b1000011 %
b1000010 +
b10000111 &
1"
#2040000
b10001000 &
0"
#2055000
b1000011 +
b1000100 %
b10001001 &
1"
#2070000
b10001010 &
0"
#2085000
b1000101 %
b1000100 +
b10001011 &
1"
#2100000
b10001100 &
0"
#2115000
b1000101 +
b1000110 %
b10001101 &
1"
#2130000
b10001110 &
0"
#2145000
b1000111 %
b1000110 +
b10001111 &
1"
#2160000
b10010000 &
0"
#2175000
b1000111 +
b1001000 %
b10010001 &
1"
#2190000
b10010010 &
0"
#2205000
b1001001 %
b1001000 +
b10010011 &
1"
#2220000
b10010100 &
0"
#2235000
b1001001 +
b1001010 %
b10010101 &
1"
#2250000
b10010110 &
0"
#2265000
b1001011 %
b1001010 +
b10010111 &
1"
#2280000
b10011000 &
0"
#2295000
b1001011 +
b1001100 %
b10011001 &
1"
#2310000
b10011010 &
0"
#2325000
b1001101 %
b1001100 +
b10011011 &
1"
#2340000
b10011100 &
0"
#2355000
b1001101 +
b1001110 %
b10011101 &
1"
#2370000
b10011110 &
0"
#2385000
b1001111 %
b1001110 +
b10011111 &
1"
#2400000
b10100000 &
0"
#2415000
b1001111 +
b1010000 %
b10100001 &
1"
#2430000
b10100010 &
0"
#2445000
b1010001 %
b1010000 +
b10100011 &
1"
#2460000
b10100100 &
0"
#2475000
b1010001 +
b1010010 %
b10100101 &
1"
#2490000
b10100110 &
0"
#2505000
b1010011 %
b1010010 +
b10100111 &
1"
#2520000
b10101000 &
0"
#2535000
b1010011 +
b1010100 %
b10101001 &
1"
#2550000
b10101010 &
0"
#2565000
b1010101 %
b1010100 +
b10101011 &
1"
#2580000
b10101100 &
0"
#2595000
b1010101 +
b1010110 %
b10101101 &
1"
#2610000
b10101110 &
0"
#2625000
b1010111 %
b1010110 +
b10101111 &
1"
#2640000
b10110000 &
0"
#2655000
b1010111 +
b1011000 %
b10110001 &
1"
#2670000
b10110010 &
0"
#2685000
b1011001 %
b1011000 +
b10110011 &
1"
#2700000
b10110100 &
0"
#2715000
b1011001 +
b1011010 %
b10110101 &
1"
#2730000
b10110110 &
0"
#2745000
b1011011 %
b1011010 +
b10110111 &
1"
#2760000
b10111000 &
0"
#2775000
b1011011 +
b1011100 %
b10111001 &
1"
#2790000
b10111010 &
0"
#2805000
b1011101 %
b1011100 +
b10111011 &
1"
#2820000
b10111100 &
0"
#2835000
b1011101 +
b1011110 %
b10111101 &
1"
#2850000
b10111110 &
0"
#2865000
b1011111 %
b1011110 +
b10111111 &
1"
#2880000
b11000000 &
0"
#2895000
b1011111 +
b1100000 %
b11000001 &
1"
#2910000
b11000010 &
0"
#2925000
b1100001 %
b1100000 +
b11000011 &
1"
#2940000
b11000100 &
0"
#2955000
b1100001 +
b1100010 %
b11000101 &
1"
#2970000
b11000110 &
0"
#2985000
b1100011 %
b1100010 +
b11000111 &
1"
#3000000
b11001000 &
0"
#3015000
b1100011 +
b1100100 %
b11001001 &
1"
#3030000
b11001010 &
0"
#3045000
b1100101 %
b1100100 +
b11001011 &
1"
#3060000
b11001100 &
0"
#3075000
b1100101 +
b1100110 %
b11001101 &
1"
#3090000
b11001110 &
0"
#3105000
b1100111 %
b1100110 +
b11001111 &
1"
#3120000
b11010000 &
0"
#3135000
b1100111 +
b1101000 %
b11010001 &
1"
#3150000
b11010010 &
0"
#3165000
b1101001 %
b1101000 +
b11010011 &
1"
#3180000
b11010100 &
0"
#3195000
b1101001 +
b1101010 %
b11010101 &
1"
#3210000
b11010110 &
0"
#3225000
b1101011 %
b1101010 +
b11010111 &
1"
#3240000
b11011000 &
0"
#3255000
b1101011 +
b1101100 %
b11011001 &
1"
#3270000
b11011010 &
0"
#3285000
b1101101 %
b1101100 +
b11011011 &
1"
#3300000
b11011100 &
0"
#3315000
b1101101 +
b1101110 %
b11011101 &
1"
#3330000
b11011110 &
0"
#3345000
b1101111 %
b1101110 +
b11011111 &
1"
#3360000
b11100000 &
0"
#3375000
b1101111 +
b1110000 %
b11100001 &
1"
#3390000
b11100010 &
0"
#3405000
b1110001 %
b1110000 +
b11100011 &
1"
#3420000
b11100100 &
0"
#3435000
b1110001 +
b1110010 %
b11100101 &
1"
#3450000
b11100110 &
0"
#3465000
b1110011 %
b1110010 +
b11100111 &
1"
#3480000
b11101000 &
0"
#3495000
b1110011 +
b1110100 %
b11101001 &
1"
#3510000
b11101010 &
0"
#3525000
b1110101 %
b1110100 +
b11101011 &
1"
#3540000
b11101100 &
0"
#3555000
b1110101 +
b1110110 %
b11101101 &
1"
#3570000
b11101110 &
0"
#3585000
b1110111 %
b1110110 +
b11101111 &
1"
#3600000
b11110000 &
0"
#3615000
b1110111 +
b1111000 %
b11110001 &
1"
#3630000
b11110010 &
0"
#3645000
b1111001 %
b1111000 +
b11110011 &
1"
#3660000
b11110100 &
0"
#3675000
b1111001 +
b1111010 %
b11110101 &
1"
#3690000
b11110110 &
0"
#3705000
b1111011 %
b1111010 +
b11110111 &
1"
#3720000
b11111000 &
0"
#3735000
b1111011 +
b1111100 %
b11111001 &
1"
#3750000
b11111010 &
0"
#3765000
b1111101 %
b1111100 +
b11111011 &
1"
#3780000
b11111100 &
0"
#3795000
b1111101 +
b1111110 %
b11111101 &
1"
#3810000
b11111110 &
0"
#3825000
b1111111 %
b1111110 +
b11111111 &
1"
#3840000
b100000000 &
0"
#3855000
b1111111 +
b10000000 %
b100000001 &
1"
#3870000
b100000010 &
0"
#3885000
b10000001 %
b10000000 +
b100000011 &
1"
#3900000
b100000100 &
0"
#3915000
b10000001 +
b10000010 %
b100000101 &
1"
#3930000
b100000110 &
0"
#3945000
b10000011 %
b10000010 +
b100000111 &
1"
#3960000
b100001000 &
0"
#3975000
b10000011 +
b10000100 %
b100001001 &
1"
#3990000
b100001010 &
0"
#4005000
b10000101 %
b10000100 +
b100001011 &
1"
#4020000
b100001100 &
0"
#4035000
b10000101 +
b10000110 %
b100001101 &
1"
#4050000
b100001110 &
0"
#4065000
b10000111 %
b10000110 +
b100001111 &
1"
#4080000
b100010000 &
0"
#4095000
b10000111 +
b10001000 %
b100010001 &
1"
#4110000
b100010010 &
0"
#4125000
b10001001 %
b10001000 +
b100010011 &
1"
#4140000
b100010100 &
0"
#4155000
b10001001 +
b10001010 %
b100010101 &
1"
#4170000
b100010110 &
0"
#4185000
b10001011 %
b10001010 +
b100010111 &
1"
#4200000
b100011000 &
0"
#4215000
b10001011 +
b10001100 %
b100011001 &
1"
#4230000
b100011010 &
0"
#4245000
b10001101 %
b10001100 +
b100011011 &
1"
#4260000
b100011100 &
0"
#4275000
b10001101 +
b10001110 %
b100011101 &
1"
#4290000
b100011110 &
0"
#4305000
b10001111 %
b10001110 +
b100011111 &
1"
#4320000
b100100000 &
0"
#4335000
b10001111 +
b10010000 %
b100100001 &
1"
#4350000
b100100010 &
0"
#4365000
b10010001 %
b10010000 +
b100100011 &
1"
#4380000
b100100100 &
0"
#4395000
0*
b0 +
b10010010 %
b100100101 &
1"
#4410000
b100100110 &
0"
#4425000
b10010011 %
b1 +
b100100111 &
1"
#4440000
b100101000 &
0"
#4455000
b10 +
b10010100 %
b100101001 &
1"
#4470000
b100101010 &
0"
#4485000
b10010101 %
b11 +
b100101011 &
1"
#4500000
b100101100 &
0"
#4515000
b100 +
b10010110 %
b100101101 &
1"
#4530000
b100101110 &
0"
#4545000
b10010111 %
b101 +
b100101111 &
1"
#4560000
b100110000 &
0"
#4575000
b110 +
b10011000 %
b100110001 &
1"
#4590000
b100110010 &
0"
#4605000
b10011001 %
b111 +
b100110011 &
1"
#4620000
b100110100 &
0"
#4635000
b1000 +
b10011010 %
b100110101 &
1"
#4650000
b100110110 &
0"
#4665000
b10011011 %
b1001 +
b100110111 &
1"
#4680000
b100111000 &
0"
#4695000
b1010 +
b10011100 %
b100111001 &
1"
#4710000
b100111010 &
0"
#4725000
b10011101 %
b1011 +
b100111011 &
1"
#4740000
b100111100 &
0"
#4755000
b1100 +
b10011110 %
b100111101 &
1"
#4770000
b100111110 &
0"
#4785000
b10011111 %
b1101 +
b100111111 &
1"
#4800000
b101000000 &
0"
#4815000
b1110 +
b10100000 %
b101000001 &
1"
#4830000
b101000010 &
0"
#4845000
b10100001 %
b1111 +
b101000011 &
1"
#4860000
b101000100 &
0"
#4875000
b10000 +
b10100010 %
b101000101 &
1"
#4890000
b101000110 &
0"
#4905000
b10100011 %
b10001 +
b101000111 &
1"
#4920000
b101001000 &
0"
#4935000
b10010 +
b10100100 %
b101001001 &
1"
#4950000
b101001010 &
0"
#4965000
b10100101 %
b10011 +
b101001011 &
1"
#4980000
b101001100 &
0"
#4995000
b10100 +
b10100110 %
b101001101 &
1"
#5010000
b101001110 &
0"
#5025000
b10100111 %
b10101 +
b101001111 &
1"
#5040000
b101010000 &
0"
#5055000
b10110 +
b10101000 %
b101010001 &
1"
#5070000
b101010010 &
0"
#5085000
b10101001 %
b10111 +
b101010011 &
1"
#5100000
b101010100 &
0"
#5115000
b11000 +
b10101010 %
b101010101 &
1"
#5130000
b101010110 &
0"
#5145000
b10101011 %
b11001 +
b101010111 &
1"
#5160000
b101011000 &
0"
#5175000
b11010 +
b10101100 %
b101011001 &
1"
#5190000
b101011010 &
0"
#5205000
b10101101 %
b11011 +
b101011011 &
1"
#5220000
b101011100 &
0"
#5235000
b11100 +
b10101110 %
b101011101 &
1"
#5250000
b101011110 &
0"
#5265000
b10101111 %
b11101 +
b101011111 &
1"
#5280000
b101100000 &
0"
#5295000
b11110 +
b10110000 %
b101100001 &
1"
#5310000
b101100010 &
0"
#5325000
b10110001 %
b11111 +
b101100011 &
1"
#5340000
b101100100 &
0"
#5355000
b100000 +
b10110010 %
b101100101 &
1"
#5370000
b101100110 &
0"
#5385000
b10110011 %
b100001 +
b101100111 &
1"
#5400000
b101101000 &
0"
#5415000
b100010 +
b10110100 %
b101101001 &
1"
#5430000
b101101010 &
0"
#5445000
b10110101 %
b100011 +
b101101011 &
1"
#5460000
b101101100 &
0"
#5475000
b100100 +
b10110110 %
b101101101 &
1"
#5490000
b101101110 &
0"
#5505000
b10110111 %
b100101 +
b101101111 &
1"
#5520000
b101110000 &
0"
#5535000
b100110 +
b10111000 %
b101110001 &
1"
#5550000
b101110010 &
0"
#5565000
b10111001 %
b100111 +
b101110011 &
1"
#5580000
b101110100 &
0"
#5595000
b101000 +
b10111010 %
b101110101 &
1"
#5610000
b101110110 &
0"
#5625000
b10111011 %
b101001 +
b101110111 &
1"
#5640000
b101111000 &
0"
#5655000
b101010 +
b10111100 %
b101111001 &
1"
#5670000
b101111010 &
0"
#5685000
b10111101 %
b101011 +
b101111011 &
1"
#5700000
b101111100 &
0"
#5715000
b101100 +
b10111110 %
b101111101 &
1"
#5730000
b101111110 &
0"
#5745000
b10111111 %
b101101 +
b101111111 &
1"
#5760000
b110000000 &
0"
#5775000
b101110 +
b11000000 %
b110000001 &
1"
#5790000
b110000010 &
0"
#5805000
b11000001 %
b101111 +
b110000011 &
1"
#5820000
b110000100 &
0"
#5835000
b110000 +
b11000010 %
b110000101 &
1"
#5850000
b110000110 &
0"
#5865000
b11000011 %
b110001 +
b110000111 &
1"
#5880000
b110001000 &
0"
#5895000
b110010 +
b11000100 %
b110001001 &
1"
#5910000
b110001010 &
0"
#5925000
b11000101 %
b110011 +
b110001011 &
1"
#5940000
b110001100 &
0"
#5955000
b110100 +
b11000110 %
b110001101 &
1"
#5970000
b110001110 &
0"
#5985000
b11000111 %
b110101 +
b110001111 &
1"
#6000000
b110010000 &
0"
#6015000
b110110 +
b11001000 %
b110010001 &
1"
#6030000
b110010010 &
0"
#6045000
b11001001 %
b110111 +
b110010011 &
1"
#6060000
b110010100 &
0"
#6075000
b111000 +
b11001010 %
b110010101 &
1"
#6090000
b110010110 &
0"
#6105000
b11001011 %
b111001 +
b110010111 &
1"
#6120000
b110011000 &
0"
#6135000
b111010 +
b11001100 %
b110011001 &
1"
#6150000
b110011010 &
0"
#6165000
b11001101 %
b111011 +
b110011011 &
1"
#6180000
b110011100 &
0"
#6195000
b111100 +
b11001110 %
b110011101 &
1"
#6210000
b110011110 &
0"
#6225000
b11001111 %
b111101 +
b110011111 &
1"
#6240000
b110100000 &
0"
#6255000
b111110 +
b11010000 %
b110100001 &
1"
#6270000
b110100010 &
0"
#6285000
b11010001 %
b111111 +
b110100011 &
1"
#6300000
b110100100 &
0"
#6315000
b1000000 +
b11010010 %
b110100101 &
1"
#6330000
b110100110 &
0"
#6345000
b11010011 %
b1000001 +
b110100111 &
1"
#6360000
b110101000 &
0"
#6375000
b1000010 +
b11010100 %
b110101001 &
1"
#6390000
b110101010 &
0"
#6405000
b11010101 %
b1000011 +
b110101011 &
1"
#6420000
b110101100 &
0"
#6435000
b1000100 +
b11010110 %
b110101101 &
1"
#6450000
b110101110 &
0"
#6465000
b11010111 %
b1000101 +
b110101111 &
1"
#6480000
b110110000 &
0"
#6495000
b1000110 +
b11011000 %
b110110001 &
1"
#6510000
b110110010 &
0"
#6525000
b11011001 %
b1000111 +
b110110011 &
1"
#6540000
b110110100 &
0"
#6555000
b1001000 +
b11011010 %
b110110101 &
1"
#6570000
b110110110 &
0"
#6585000
b11011011 %
b1001001 +
b110110111 &
1"
#6600000
b110111000 &
0"
#6615000
b1001010 +
b11011100 %
b110111001 &
1"
#6630000
b110111010 &
0"
#6645000
b11011101 %
b1001011 +
b110111011 &
1"
#6660000
b110111100 &
0"
#6675000
b1001100 +
b11011110 %
b110111101 &
1"
#6690000
b110111110 &
0"
#6705000
b11011111 %
b1001101 +
b110111111 &
1"
#6720000
b111000000 &
0"
#6735000
b1001110 +
b11100000 %
b111000001 &
1"
#6750000
b111000010 &
0"
#6765000
b11100001 %
b1001111 +
b111000011 &
1"
#6780000
b111000100 &
0"
#6795000
b1010000 +
b11100010 %
b111000101 &
1"
#6810000
b111000110 &
0"
#6825000
b11100011 %
b1010001 +
b111000111 &
1"
#6840000
b111001000 &
0"
#6855000
b1010010 +
b11100100 %
b111001001 &
1"
#6870000
b111001010 &
0"
#6885000
b11100101 %
b1010011 +
b111001011 &
1"
#6900000
b111001100 &
0"
#6915000
b1010100 +
b11100110 %
b111001101 &
1"
#6930000
b111001110 &
0"
#6945000
b11100111 %
b1010101 +
b111001111 &
1"
#6960000
b111010000 &
0"
#6975000
b1010110 +
b11101000 %
b111010001 &
1"
#6990000
b111010010 &
0"
#7005000
b11101001 %
b1010111 +
b111010011 &
1"
#7020000
b111010100 &
0"
#7035000
b1011000 +
b11101010 %
b111010101 &
1"
#7050000
b111010110 &
0"
#7065000
b11101011 %
b1011001 +
b111010111 &
1"
#7080000
b111011000 &
0"
#7095000
b1011010 +
b11101100 %
b111011001 &
1"
#7110000
b111011010 &
0"
#7125000
b11101101 %
b1011011 +
b111011011 &
1"
#7140000
b111011100 &
0"
#7155000
b1011100 +
b11101110 %
b111011101 &
1"
#7170000
b111011110 &
0"
#7185000
b11101111 %
b1011101 +
b111011111 &
1"
#7200000
b111100000 &
0"
#7215000
b1011110 +
b11110000 %
b111100001 &
1"
#7230000
b111100010 &
0"
#7245000
b11110001 %
b1011111 +
b111100011 &
1"
#7260000
b111100100 &
0"
#7275000
b1100000 +
b11110010 %
b111100101 &
1"
#7290000
b111100110 &
0"
#7305000
b11110011 %
b1100001 +
b111100111 &
1"
#7320000
b111101000 &
0"
#7335000
b1100010 +
b11110100 %
b111101001 &
1"
#7350000
b111101010 &
0"
#7365000
b11110101 %
b1100011 +
b111101011 &
1"
#7380000
b111101100 &
0"
#7395000
b1100100 +
b11110110 %
b111101101 &
1"
#7410000
b111101110 &
0"
#7425000
b11110111 %
b1100101 +
b111101111 &
1"
#7440000
b111110000 &
0"
#7455000
b1100110 +
b11111000 %
b111110001 &
1"
#7470000
b111110010 &
0"
#7485000
b11111001 %
b1100111 +
b111110011 &
1"
#7500000
b111110100 &
0"
#7515000
b1101000 +
b11111010 %
b111110101 &
1"
#7530000
b111110110 &
0"
#7545000
b11111011 %
b1101001 +
b111110111 &
1"
#7560000
b111111000 &
0"
#7575000
b1101010 +
b11111100 %
b111111001 &
1"
#7590000
b111111010 &
0"
#7605000
b11111101 %
b1101011 +
b111111011 &
1"
#7620000
b111111100 &
0"
#7635000
b1101100 +
b11111110 %
b111111101 &
1"
#7650000
b111111110 &
0"
#7665000
b11111111 %
b1101101 +
b111111111 &
1"
#7680000
b1000000000 &
0"
#7695000
b1101110 +
b100000000 %
b1000000001 &
1"
#7710000
b1000000010 &
0"
#7725000
b100000001 %
b1101111 +
b1000000011 &
1"
#7740000
b1000000100 &
0"
#7755000
b1110000 +
b100000010 %
b1000000101 &
1"
#7770000
b1000000110 &
0"
#7785000
b100000011 %
b1110001 +
b1000000111 &
1"
#7800000
b1000001000 &
0"
#7815000
b1110010 +
b100000100 %
b1000001001 &
1"
#7830000
b1000001010 &
0"
#7845000
b100000101 %
b1110011 +
b1000001011 &
1"
#7860000
b1000001100 &
0"
#7875000
b1110100 +
b100000110 %
b1000001101 &
1"
#7890000
b1000001110 &
0"
#7905000
b100000111 %
b1110101 +
b1000001111 &
1"
#7920000
b1000010000 &
0"
#7935000
b1110110 +
b100001000 %
b1000010001 &
1"
#7950000
b1000010010 &
0"
#7965000
b100001001 %
b1110111 +
b1000010011 &
1"
#7980000
b1000010100 &
0"
#7995000
b1111000 +
b100001010 %
b1000010101 &
1"
#8010000
b1000010110 &
0"
#8025000
b100001011 %
b1111001 +
b1000010111 &
1"
#8040000
b1000011000 &
0"
#8055000
b1111010 +
b100001100 %
b1000011001 &
1"
#8070000
b1000011010 &
0"
#8085000
b100001101 %
b1111011 +
b1000011011 &
1"
#8100000
b1000011100 &
0"
#8115000
b1111100 +
b100001110 %
b1000011101 &
1"
#8130000
b1000011110 &
0"
#8145000
b100001111 %
b1111101 +
b1000011111 &
1"
#8160000
b1000100000 &
0"
#8175000
b1111110 +
b100010000 %
b1000100001 &
1"
#8190000
b1000100010 &
0"
#8205000
b100010001 %
b1111111 +
b1000100011 &
1"
#8220000
b1000100100 &
0"
#8235000
b10000000 +
b100010010 %
b1000100101 &
1"
#8250000
b1000100110 &
0"
#8265000
b100010011 %
b10000001 +
b1000100111 &
1"
#8280000
b1000101000 &
0"
#8295000
b10000010 +
b100010100 %
b1000101001 &
1"
#8310000
b1000101010 &
0"
#8325000
b100010101 %
b10000011 +
b1000101011 &
1"
#8340000
b1000101100 &
0"
#8355000
b10000100 +
b100010110 %
b1000101101 &
1"
#8370000
b1000101110 &
0"
#8385000
b100010111 %
b10000101 +
b1000101111 &
1"
#8400000
b1000110000 &
0"
#8415000
b10000110 +
b100011000 %
b1000110001 &
1"
#8430000
b1000110010 &
0"
#8445000
b100011001 %
b10000111 +
b1000110011 &
1"
#8460000
b1000110100 &
0"
#8475000
b10001000 +
b100011010 %
b1000110101 &
1"
#8490000
b1000110110 &
0"
#8505000
b100011011 %
b10001001 +
b1000110111 &
1"
#8520000
b1000111000 &
0"
#8535000
b10001010 +
b100011100 %
b1000111001 &
1"
#8550000
b1000111010 &
0"
#8565000
b100011101 %
b10001011 +
b1000111011 &
1"
#8580000
b1000111100 &
0"
#8595000
b10001100 +
b100011110 %
b1000111101 &
1"
#8610000
b1000111110 &
0"
#8625000
b100011111 %
b10001101 +
b1000111111 &
1"
#8640000
b1001000000 &
0"
#8655000
b10001110 +
b100100000 %
b1001000001 &
1"
#8670000
b1001000010 &
0"
#8685000
b100100001 %
b10001111 +
b1001000011 &
1"
#8700000
b1001000100 &
0"
#8715000
b10010000 +
b100100010 %
b1001000101 &
1"
#8730000
b1001000110 &
0"
